dlglab/__init__.py
dlglab-0.6.0.dist-info/licenses/LICENSE
dlglab-0.6.0.dist-info/METADATA
dlglab-0.6.0.dist-info/WHEEL
dlglab-0.6.0.dist-info/top_level.txt
dlglab-0.6.0.dist-info/RECORD
