Metadata-Version: 2.4
Name: dlglab
Version: 0.6.0
Summary: A simple package that prints hello world
Home-page: https://github.com/tchirag03/dlglab
Author: Chirag T
Author-email: t.chiru2005@gmail.com
Classifier: Programming Language :: Python :: 3
Classifier: License :: OSI Approved :: MIT License
Classifier: Operating System :: OS Independent
Requires-Python: >=3.6
License-File: LICENSE
Dynamic: author
Dynamic: author-email
Dynamic: classifier
Dynamic: description
Dynamic: description-content-type
Dynamic: home-page
Dynamic: license-file
Dynamic: requires-python
Dynamic: summary
